snipsskills/__init__.py
snipsskills/cli.py
snipsskills/snipsskills
snipsskills/commands/__init__.py
snipsskills/commands/base.py
snipsskills/commands/run.py
snipsskills/commands/scaffold.py
snipsskills/commands/assistant/__init__.py
snipsskills/commands/assistant/fetch.py
snipsskills/commands/assistant/load.py
snipsskills/commands/install/__init__.py
snipsskills/commands/install/addon.py
snipsskills/commands/install/bluetooth.py
snipsskills/commands/install/install.py
snipsskills/commands/install/skill.py
snipsskills/commands/install/skills.py
snipsskills/commands/session/__init__.py
snipsskills/commands/session/login.py
snipsskills/commands/session/logout.py
snipsskills/commands/setup/__init__.py
snipsskills/commands/setup/microphone.py
snipsskills/commands/setup/speaker.py
snipsskills/commands/setup/systemd/__init__.py
snipsskills/commands/setup/systemd/bluetooth.py
snipsskills/commands/setup/systemd/snips.py
snipsskills/commands/setup/systemd/snipsskills.py
snipsskills/config/__init__.py
snipsskills/config/asoundrc/__init__.py
snipsskills/config/asoundrc/asound.conf.speakerbonnet
snipsskills/config/asoundrc/asoundrc.default
snipsskills/config/asoundrc/asoundrc.jabra
snipsskills/config/asoundrc/asoundrc.respeaker
snipsskills/config/asoundrc/asoundrc.speakerbonnet
snipsskills/config/drivers/__init__.py
snipsskills/config/drivers/adafruit_bonnet.sh
snipsskills/config/systemd/__init__.py
snipsskills/config/systemd/snips.service
snipsskills/config/systemd/snipsble.service
snipsskills/config/systemd/snipsskills.service
snipsskills/models/__init__.py
snipsskills/models/intentdef.py
snipsskills/models/skilldef.py
snipsskills/templates/LICENSE.txt
snipsskills/templates/MANIFEST.in
snipsskills/templates/README.rst
snipsskills/templates/__init__.py
snipsskills/templates/intent_registry_template.py
snipsskills/templates/intent_template.py
snipsskills/templates/lint.cfg
snipsskills/templates/setup.cfg
snipsskills-0.1.6.26.dist-info/DESCRIPTION.rst
snipsskills-0.1.6.26.dist-info/METADATA
snipsskills-0.1.6.26.dist-info/RECORD
snipsskills-0.1.6.26.dist-info/WHEEL
snipsskills-0.1.6.26.dist-info/entry_points.txt
snipsskills-0.1.6.26.dist-info/metadata.json
snipsskills-0.1.6.26.dist-info/top_level.txt
