Metadata-Version: 2.0
Name: snipsskills
Version: 0.1.6.26
Summary: Snips Skills Manager
Home-page: https://github.com/snipsco/snipsskills
Author: Snips
Author-email: michael.fester@snips.ai
License: MIT
Keywords: cli,snips
Platform: UNKNOWN
Requires-Dist: docopt
Requires-Dist: python-dateutil
Requires-Dist: Jinja2
Requires-Dist: pyyaml
Requires-Dist: pip
Requires-Dist: snipsskillscore
Provides-Extra: test
Requires-Dist: coverage; extra == 'test'
Requires-Dist: pytest; extra == 'test'
Requires-Dist: pytest-cov; extra == 'test'
